README.md
setup.cfg
setup.py
Textyplot.egg-info/PKG-INFO
Textyplot.egg-info/SOURCES.txt
Textyplot.egg-info/dependency_links.txt
Textyplot.egg-info/entry_points.txt
Textyplot.egg-info/top_level.txt
textyplot/__init__.py
textyplot/__main__.py
textyplot/textyplot.py