Metadata-Version: 1.0
Name: Textyplot
Version: 1.0
Summary: UNKNOWN
Home-page: https://github.com/michaelkrukov/textyplot
Author: Krukov Michael
Author-email: krukov.michael@ya.ru
License: UNKNOWN
Keywords: diagram,graph,plotting,text
Platform: UNKNOWN
